{
  "timestamp": "2026-02-24T16:28:02.406400+00:00",
  "mode": "debug",
  "question": "What is the primary reason for the ENOENT (no such file or directory) error in the read_file tool, as observed in the execution log at 2026-02-24T16:26:53.607Z, and can this error be resolved by adjusting the Python path or by updating the drift_api.py file?",
  "oracle_engine": "groq-llama-70b",
  "oracle_response": "The ENOENT (no such file or directory) error in the read_file tool, as observed in the execution log at 2026-02-24T16:26:53.607Z, is primarily caused by the tool's inability to locate the specified file. This error typically occurs when the file path provided to the read_file tool is incorrect, incomplete, or the file does not exist at the specified location. The tool attempts to access the file system to read the file, but since it cannot find the file, it raises the ENOENT error. This issue is not directly related to the Python path or the drift_api.py file. Instead, it is a problem with the file path or the file's existence.\n\nAdjusting the Python path is unlikely to resolve the ENOENT error in this case. The Python path is used to locate Python modules and packages, not files accessed by tools like read_file. Unless the file being accessed is a Python module or package, changing the Python path will not help. Similarly, updating the drift_api.py file may not resolve the issue unless the file path or the file access logic is modified within the drift_api.py file. If the drift_api.py file is responsible for constructing the file path or accessing the file, then updating it to correct the file path or handle file access correctly might resolve the issue. However, if the issue is solely with the file path or the file's existence, updating the drift_api.py file will not be sufficient to resolve the ENOENT error.\n\nTo resolve the ENOENT error, it is essential to verify the file path and ensure that the file exists at the specified location. This can be done by checking the file system, confirming the file name and path, and ensuring that the file is not deleted or moved. If the file path is constructed dynamically, it may be necessary to review the logic that generates the file path to ensure it is correct. Additionally, implementing error handling mechanisms, such as checking if the file exists before attempting to read it, can help mitigate the ENOENT error and provide more informative error messages. By addressing the root cause of the issue, which is the incorrect or non-existent file path, the ENOENT error can be resolved, and the read_file tool can function as expected.",
  "actions": [
    {
      "action": "Verify the file path and existence of the file accessed by the read_file tool",
      "tool": "manage_cooldown",
      "priority": "high",
      "details": "Check the file system at the specified location and confirm the file name and path in the code"
    },
    {
      "action": "Implement error handling to check if the file exists before attempting to read it",
      "tool": "exec",
      "priority": "medium",
      "details": "Add a try-except block to check for the ENOENT error and handle it by checking if the file exists"
    },
    {
      "action": "Review the logic that generates the file path and correct it if necessary",
      "tool": "write_file",
      "priority": "low",
      "details": "Check the drift_api.py file for any dynamic file path construction and update the logic if incorrect"
    }
  ]
}